[{"network_depth":0,"total_gates":104,"network_size":0,"preprocess_weight":0},{"network_depth":0,"total_gates":104,"network_size":0,"preprocess_weight":0},{"network_depth":111,"total_gates":73609,"network_size":1678616,"preprocess_weight":79543920},{"network_depth":111,"total_gates":118772,"network_size":2820944,"preprocess_weight":131450640},{"network_depth":111,"total_gates":118772,"network_size":2820944,"preprocess_weight":131450640},{"network_depth":111,"total_gates":118772,"network_size":2820944,"preprocess_weight":131450640},{"network_depth":111,"total_gates":118772,"network_size":2820944,"preprocess_weight":131450640},{"network_depth":111,"total_gates":118772,"network_size":2820944,"preprocess_weight":131450640},{"network_depth":116,"total_gates":118865,"network_size":2821998,"preprocess_weight":131453740},{"network_depth":117,"total_gates":119904,"network_size":2830906,"preprocess_weight":131479940},{"network_depth":118,"total_gates":119906,"network_size":2830940,"preprocess_weight":131480040},{"network_depth":118,"total_gates":119906,"network_size":2830940,"preprocess_weight":131480040},{"network_depth":119,"total_gates":119907,"network_size":2830974,"preprocess_weight":131480140},{"network_depth":119,"total_gates":119907,"network_size":2830974,"preprocess_weight":131480140},{"network_depth":119,"total_gates":119919,"network_size":2831110,"preprocess_weight":131480540},{"network_depth":119,"total_gates":120958,"network_size":2840018,"preprocess_weight":131506740},{"network_depth":119,"total_gates":120960,"network_size":2840052,"preprocess_weight":131506840},{"network_depth":120,"total_gates":120962,"network_size":2840086,"preprocess_weight":131506940},{"network_depth":121,"total_gates":120964,"network_size":2840120,"preprocess_weight":131507040},{"network_depth":121,"total_gates":120965,"network_size":2840120,"preprocess_weight":131507040},{"network_depth":121,"total_gates":120967,"network_size":2840120,"preprocess_weight":131507040},{"network_depth":123,"total_gates":122872,"network_size":2913929,"preprocess_weight":133932490}]